{
  "resolvedId": "D:/Projects/Nabtaty-dashboard-de3bd56d6663c71275c3f076b188500fce6955c7/node_modules/vuetify/lib/components/VBtnToggle/VBtnToggle.css",
  "transforms": [
    {
      "name": "vite:load-fallback",
      "result": ".v-btn-toggle > .v-btn.v-btn--active:not(.v-btn--disabled) > .v-btn__overlay {\n  opacity: calc(var(--v-activated-opacity) * var(--v-theme-overlay-multiplier));\n}\n.v-btn-toggle > .v-btn.v-btn--active:not(.v-btn--disabled):hover > .v-btn__overlay {\n  opacity: calc((var(--v-activated-opacity) + var(--v-hover-opacity)) * var(--v-theme-overlay-multiplier));\n}\n.v-btn-toggle > .v-btn.v-btn--active:not(.v-btn--disabled):focus-visible > .v-btn__overlay {\n  opacity: calc((var(--v-activated-opacity) + var(--v-focus-opacity)) * var(--v-theme-overlay-multiplier));\n}\n@supports not selector(:focus-visible) {\n  .v-btn-toggle > .v-btn.v-btn--active:not(.v-btn--disabled):focus > .v-btn__overlay {\n    opacity: calc((var(--v-activated-opacity) + var(--v-focus-opacity)) * var(--v-theme-overlay-multiplier));\n  }\n}",
      "start": 1731941020307,
      "end": 1731941020705,
      "sourcemaps": null
    },
    {
      "name": "nuxt:layer-aliasing",
      "start": 1731941020705,
      "end": 1731941020705,
      "order": "pre"
    },
    {
      "name": "nuxt:server-devonly:transform",
      "start": 1731941020705,
      "end": 1731941020705,
      "order": "pre"
    },
    {
      "name": "unplugin-vue-i18n",
      "start": 1731941020705,
      "end": 1731941020705,
      "order": "pre"
    },
    {
      "name": "nuxt:client-fallback-auto-id",
      "start": 1731941020705,
      "end": 1731941020705,
      "order": "pre"
    },
    {
      "name": "vite:css",
      "result": ".v-btn-toggle>.v-btn.v-btn--active:not(.v-btn--disabled)>.v-btn__overlay{opacity:calc(var(--v-activated-opacity)*var(--v-theme-overlay-multiplier))}.v-btn-toggle>.v-btn.v-btn--active:not(.v-btn--disabled):hover>.v-btn__overlay{opacity:calc((var(--v-activated-opacity) + var(--v-hover-opacity))*var(--v-theme-overlay-multiplier))}.v-btn-toggle>.v-btn.v-btn--active:not(.v-btn--disabled):focus-visible>.v-btn__overlay{opacity:calc((var(--v-activated-opacity) + var(--v-focus-opacity))*var(--v-theme-overlay-multiplier))}@supports not selector(:focus-visible){.v-btn-toggle>.v-btn.v-btn--active:not(.v-btn--disabled):focus>.v-btn__overlay{opacity:calc((var(--v-activated-opacity) + var(--v-focus-opacity))*var(--v-theme-overlay-multiplier))}}",
      "start": 1731941020705,
      "end": 1731941020719,
      "order": "normal",
      "sourcemaps": {
        "mappings": ""
      }
    },
    {
      "name": "vite:esbuild",
      "start": 1731941020720,
      "end": 1731941020720,
      "order": "normal"
    },
    {
      "name": "vite:json",
      "start": 1731941020720,
      "end": 1731941020720,
      "order": "normal"
    },
    {
      "name": "vite:worker",
      "start": 1731941020720,
      "end": 1731941020720,
      "order": "normal"
    },
    {
      "name": "vite:vue",
      "start": 1731941020720,
      "end": 1731941020720,
      "order": "normal"
    },
    {
      "name": "vite:vue-jsx",
      "start": 1731941020720,
      "end": 1731941020720,
      "order": "normal"
    },
    {
      "name": "replace",
      "start": 1731941020720,
      "end": 1731941020720,
      "order": "normal"
    },
    {
      "name": "nuxt:remove-plugin-metadata",
      "start": 1731941020720,
      "end": 1731941020720,
      "order": "normal"
    },
    {
      "name": "nuxt:chunk-error",
      "start": 1731941020720,
      "end": 1731941020720,
      "order": "normal"
    },
    {
      "name": "nuxt:components:imports",
      "start": 1731941020720,
      "end": 1731941020720,
      "order": "normal"
    },
    {
      "name": "replace",
      "start": 1731941020720,
      "end": 1731941020720,
      "order": "normal"
    },
    {
      "name": "ssr-styles",
      "start": 1731941020720,
      "end": 1731941020720,
      "order": "normal"
    },
    {
      "name": "vite:define",
      "start": 1731941020720,
      "end": 1731941020720,
      "order": "normal"
    },
    {
      "name": "vite:css-post",
      "result": "",
      "start": 1731941020720,
      "end": 1731941020720,
      "order": "normal",
      "sourcemaps": {
        "mappings": ""
      }
    },
    {
      "name": "vite:build-html",
      "start": 1731941020721,
      "end": 1731941020721,
      "order": "normal"
    },
    {
      "name": "vite:worker-import-meta-url",
      "start": 1731941020721,
      "end": 1731941020721,
      "order": "normal"
    },
    {
      "name": "vite:asset-import-meta-url",
      "start": 1731941020721,
      "end": 1731941020721,
      "order": "normal"
    },
    {
      "name": "commonjs",
      "start": 1731941020721,
      "end": 1731941020721,
      "order": "normal"
    },
    {
      "name": "vite:dynamic-import-vars",
      "start": 1731941020721,
      "end": 1731941020721,
      "order": "normal"
    },
    {
      "name": "vite:import-glob",
      "start": 1731941020721,
      "end": 1731941020721,
      "order": "normal"
    },
    {
      "name": "nuxt:composable-keys",
      "start": 1731941020721,
      "end": 1731941020721,
      "order": "post"
    },
    {
      "name": "nuxtjs:i18n-macros-transform",
      "start": 1731941020721,
      "end": 1731941020721,
      "order": "post"
    },
    {
      "name": "nuxtjs:i18n-resource",
      "start": 1731941020721,
      "end": 1731941020721,
      "order": "post"
    },
    {
      "name": "nuxtjs:i18n-meta-deprecation",
      "start": 1731941020721,
      "end": 1731941020721,
      "order": "post"
    },
    {
      "name": "unplugin-vue-components",
      "start": 1731941020721,
      "end": 1731941020721,
      "order": "post"
    },
    {
      "name": "nuxt:imports-transform",
      "start": 1731941020721,
      "end": 1731941020721,
      "order": "post"
    },
    {
      "name": "unctx:transform",
      "start": 1731941020721,
      "end": 1731941020721,
      "order": "post"
    },
    {
      "name": "nuxt:pages-macros-transform",
      "start": 1731941020721,
      "end": 1731941020721,
      "order": "post"
    },
    {
      "name": "nuxt:runtime-paths-dep",
      "start": 1731941020721,
      "end": 1731941020721,
      "order": "post"
    },
    {
      "name": "nuxt:route-injection-plugin",
      "start": 1731941020721,
      "end": 1731941020721,
      "order": "post"
    },
    {
      "name": "nuxt:components-loader",
      "start": 1731941020721,
      "end": 1731941020721,
      "order": "post"
    },
    {
      "name": "nuxt:tree-shake-composables:transform",
      "start": 1731941020721,
      "end": 1731941020721,
      "order": "post"
    },
    {
      "name": "vite:build-import-analysis",
      "start": 1731941020721,
      "end": 1731941020721,
      "order": "normal"
    },
    {
      "name": "vite:reporter",
      "start": 1731941020721,
      "end": 1731941020721,
      "order": "normal"
    }
  ]
}
